Metadata-Version: 2.1
Name: example-pkg-teste-in8utils-rangel
Version: 0.0.1
Summary: A small example package
Home-page: https://github.com/pypa/sampleproject
Author: Marcelo Rangel
Author-email: marcelojrrangel@gmail.com
License: UNKNOWN
Platform: UNKNOWN
Classifier: Programming Language :: Python :: 3
Classifier: License :: OSI Approved :: MIT License
Classifier: Operating System :: OS Independent
Requires-Dist: bleach (==3.1.0)
Requires-Dist: certifi (==2019.9.11)
Requires-Dist: chardet (==3.0.4)
Requires-Dist: docutils (==0.15.2)
Requires-Dist: idna (==2.8)
Requires-Dist: mysqlclient (==1.4.6)
Requires-Dist: pkginfo (==1.5.0.1)
Requires-Dist: Pygments (==2.4.2)
Requires-Dist: PyMySQL (==0.9.3)
Requires-Dist: python-dotenv (==0.10.3)
Requires-Dist: readme-renderer (==24.0)
Requires-Dist: requests (==2.22.0)
Requires-Dist: requests-toolbelt (==0.9.1)
Requires-Dist: sentry-sdk (==0.12.3)
Requires-Dist: six (==1.12.0)
Requires-Dist: SQLAlchemy (==1.3.13)
Requires-Dist: tqdm (==4.36.1)
Requires-Dist: twine (==2.0.0)
Requires-Dist: urllib3 (==1.25.6)
Requires-Dist: webencodings (==0.5.1)
